README.md
setup.py
eidetic/__init__.py
eidetic/abc.py
eidetic/cache.py
eidetic/func.py
eidetic/keys.py
eidetic/lfu.py
eidetic/lru.py
eidetic/rr.py
eidetic/sqlite3.py
eidetic/ttl.py
eidetic.egg-info/PKG-INFO
eidetic.egg-info/SOURCES.txt
eidetic.egg-info/dependency_links.txt
eidetic.egg-info/requires.txt
eidetic.egg-info/top_level.txt