Metadata-Version: 1.1
Name: eidetic
Version: 2018.12.2
Summary: Caching designed for scientific computing
Home-page: https://github.com/olirice/eidetic
Author: Oliver Rice
Author-email: oliver@oliverrice.com
License: MIT
Platform: UNKNOWN
Classifier: Development Status :: 4 - Beta
Classifier: Natural Language :: English
Classifier: Operating System :: OS Independent
Classifier: Programming Language :: Python
Classifier: Programming Language :: Python :: 3
Classifier: Programming Language :: Python :: 3.6
